nbib/__init__.py
nbib/_parsing.py
nbib/_structure.py
nbib/_tags.py
nbib/exceptions.py
nbib-0.3.2.dist-info/LICENSE
nbib-0.3.2.dist-info/METADATA
nbib-0.3.2.dist-info/WHEEL
nbib-0.3.2.dist-info/top_level.txt
nbib-0.3.2.dist-info/RECORD
