Metadata-Version: 2.1
Name: nbib
Version: 0.3.2
Summary: PubMed nbib citation format parser
Home-page: https://github.com/holub008/nbib
Author: Karl Holub
Author-email: karljholub@gmail.com
License: UNKNOWN
Platform: UNKNOWN
Classifier: Programming Language :: Python :: 3
Classifier: License :: OSI Approved :: MIT License
Classifier: Operating System :: OS Independent
Requires-Python: >=3.6
Requires-Dist: dateutils
